displate/__init__.py
displate-0.1.0.dist-info/LICENSE
displate-0.1.0.dist-info/WHEEL
displate-0.1.0.dist-info/METADATA
displate-0.1.0.dist-info/RECORD
