Metadata-Version: 2.1
Name: displate
Version: 0.1.0
Summary: a boilterplate coder writter command line utility for discord.py
License: LICENCE
Author: NaviTheCoderboi
Author-email: navindersingh568@gmail.com
Requires-Python: >=3.10,<4.0
Classifier: Development Status :: 2 - Pre-Alpha
Classifier: License :: Other/Proprietary License
Classifier: Programming Language :: Python :: 3
Classifier: Programming Language :: Python :: 3.10
Classifier: Programming Language :: Python :: 3.9
Requires-Dist: click (>=8.1.3,<9.0.0)
